animalai_train/__init__.py
animalai_train/curriculum_aai.py
animalai_train/environment_factory_aai.py
animalai_train/meta_curriculum_aai.py
animalai_train/run_options_aai.py
animalai_train/run_training_aai.py
animalai_train/simple_env_manager_aai.py
animalai_train/subprocess_env_manager_aai.py
animalai_train/trainer_controller_aai.py
animalai_train-2.0.0.dist-info/METADATA
animalai_train-2.0.0.dist-info/WHEEL
animalai_train-2.0.0.dist-info/top_level.txt
animalai_train-2.0.0.dist-info/RECORD
